pycluon/_pycluon.cpython-37m-x86_64-linux-gnu.so
pycluon/importer.py
pycluon/__init__.py
pycluon/scripts.py
pycluon/resources/cluon_data_structures.odvd
pycluon/bin/cluon-OD4toStdout
pycluon/bin/cluon-OD4toJSON
pycluon/bin/cluon-rec2csv
pycluon/bin/cluon-replay
pycluon/bin/cluon-msc
pycluon/bin/cluon-livefeed
pycluon/bin/cluon-filter
pycluon/bin/cluon-LCMtoJSON
pycluon-0.2.3.dist-info/RECORD
pycluon-0.2.3.dist-info/WHEEL
pycluon-0.2.3.dist-info/LICENSE
pycluon-0.2.3.dist-info/METADATA
pycluon-0.2.3.dist-info/top_level.txt
pycluon-0.2.3.dist-info/entry_points.txt
