Metadata-Version: 2.1
Name: pycluon
Version: 0.2.3
Summary: A python wrapper around libcluon
Home-page: https://github.com/MO-RISE/pycluon
Author: Fredrik Olsson
Author-email: fredrik.x.olsson@ri.se
Maintainer: Fredrik Olsson
Maintainer-email: fredrik.x.olsson@ri.se
License: Apache License 2.0
Requires-Python: >=3.7
License-File: LICENSE
Requires-Dist: protobuf
Requires-Dist: protoc-wheel-0
